acapy_plugin_pickup/__init__.py
acapy_plugin_pickup/acapy/__init__.py
acapy_plugin_pickup/acapy/error.py
acapy_plugin_pickup/acapy/message.py
acapy_plugin_pickup/definition.py
acapy_plugin_pickup/v2_0/__init__.py
acapy_plugin_pickup/v2_0/delivery.py
acapy_plugin_pickup/v2_0/live_mode.py
acapy_plugin_pickup/v2_0/message_types.py
acapy_plugin_pickup/v2_0/routes.py
acapy_plugin_pickup/v2_0/status.py
acapy_plugin_pickup/valid.py
acapy_plugin_pickup-0.2.0.dist-info/LICENSE
acapy_plugin_pickup-0.2.0.dist-info/METADATA
acapy_plugin_pickup-0.2.0.dist-info/WHEEL
acapy_plugin_pickup-0.2.0.dist-info/RECORD
