Metadata-Version: 2.1
Name: acapy-plugin-pickup
Version: 0.2.0
Summary: Pickup Protocol for ACA-Py
License: Apache-2.0
Author: Daniel Bluhm
Author-email: dbluhm@pm.me
Requires-Python: >=3.8,<4.0
Classifier: License :: OSI Approved :: Apache Software License
Classifier: Programming Language :: Python :: 3
Classifier: Programming Language :: Python :: 3.8
Classifier: Programming Language :: Python :: 3.9
Classifier: Programming Language :: Python :: 3.10
Classifier: Programming Language :: Python :: 3.11
Requires-Dist: aries-cloudagent[askar,bbs,indy] (==0.8.2)
Requires-Dist: pydantic (>=1.8.1,<2.0.0)
Requires-Dist: python-dateutil (>=2.8.1,<3.0.0)
Requires-Dist: typing-extensions (>=3.7.4,<4.0.0)
